shared_cache/__init__.py
shared_cache/service.py
shared_cache/shared.py
shared_cache-1.0.1.dist-info/LICENSE
shared_cache-1.0.1.dist-info/METADATA
shared_cache-1.0.1.dist-info/WHEEL
shared_cache-1.0.1.dist-info/top_level.txt
shared_cache-1.0.1.dist-info/RECORD
