Metadata-Version: 2.1
Name: shared_cache
Version: 1.0.1
Summary: Across workers shared cache for python3
Home-page: https://github.com/wassef911/shared_cache
Author: Wassef911
Author-email: wassef911@gmail.com
Keywords: python3,pypi,package
Classifier: Development Status :: 5 - Production/Stable
Classifier: Intended Audience :: Developers
Classifier: Topic :: Software Development
Classifier: Programming Language :: Python :: 3 :: Only
Classifier: License :: OSI Approved :: MIT License
Classifier: Operating System :: OS Independent
Requires-Python: >=3.8.0
License-File: LICENSE
Requires-Dist: msgpack
Provides-Extra: dev
Requires-Dist: check-manifest ; extra == 'dev'
Provides-Extra: test
Requires-Dist: coverage ; extra == 'test'
